xdaLibs/__init__.py
xdaLibs/iniconfig.py
xdaLibs-0.2.0.dist-info/LICENSE
xdaLibs-0.2.0.dist-info/METADATA
xdaLibs-0.2.0.dist-info/WHEEL
xdaLibs-0.2.0.dist-info/top_level.txt
xdaLibs-0.2.0.dist-info/RECORD
